simplelogincmd/__init__.py
simplelogincmd/cli/__init__.py
simplelogincmd/cli/commands/__init__.py
simplelogincmd/cli/commands/_config.py
simplelogincmd/cli/commands/account.py
simplelogincmd/cli/commands/account_commands/__init__.py
simplelogincmd/cli/commands/account_commands/_login.py
simplelogincmd/cli/commands/account_commands/_logout.py
simplelogincmd/cli/commands/account_commands/_mfa.py
simplelogincmd/cli/commands/account_commands/login.py
simplelogincmd/cli/commands/account_commands/logout.py
simplelogincmd/cli/commands/account_commands/mfa.py
simplelogincmd/cli/commands/alias.py
simplelogincmd/cli/commands/alias_commands/__init__.py
simplelogincmd/cli/commands/alias_commands/_activity.py
simplelogincmd/cli/commands/alias_commands/_custom.py
simplelogincmd/cli/commands/alias_commands/_delete.py
simplelogincmd/cli/commands/alias_commands/_get.py
simplelogincmd/cli/commands/alias_commands/_list.py
simplelogincmd/cli/commands/alias_commands/_random.py
simplelogincmd/cli/commands/alias_commands/_toggle.py
simplelogincmd/cli/commands/alias_commands/_update.py
simplelogincmd/cli/commands/alias_commands/activity.py
simplelogincmd/cli/commands/alias_commands/contact.py
simplelogincmd/cli/commands/alias_commands/contact_commands/__init__.py
simplelogincmd/cli/commands/alias_commands/contact_commands/_create.py
simplelogincmd/cli/commands/alias_commands/contact_commands/_delete.py
simplelogincmd/cli/commands/alias_commands/contact_commands/_list.py
simplelogincmd/cli/commands/alias_commands/contact_commands/_toggle.py
simplelogincmd/cli/commands/alias_commands/contact_commands/create.py
simplelogincmd/cli/commands/alias_commands/contact_commands/delete.py
simplelogincmd/cli/commands/alias_commands/contact_commands/list.py
simplelogincmd/cli/commands/alias_commands/contact_commands/toggle.py
simplelogincmd/cli/commands/alias_commands/custom.py
simplelogincmd/cli/commands/alias_commands/delete.py
simplelogincmd/cli/commands/alias_commands/get.py
simplelogincmd-0.5.2.dist-info/LICENSE
simplelogincmd-0.5.2.dist-info/METADATA
simplelogincmd-0.5.2.dist-info/WHEEL
simplelogincmd-0.5.2.dist-info/entry_points.txt
simplelogincmd-0.5.2.dist-info/RECORD
