Metadata-Version: 2.1
Name: simplelogincmd
Version: 0.5.2
Summary: SimpleLogin command-line application
License: MIT
Author: truthless-dev
Author-email: truthless.deviant248@simplelogin.fr
Requires-Python: >=3.10,<4.0
Classifier: License :: OSI Approved :: MIT License
Classifier: Programming Language :: Python :: 3
Classifier: Programming Language :: Python :: 3.10
Classifier: Programming Language :: Python :: 3.11
Classifier: Programming Language :: Python :: 3.12
Classifier: Programming Language :: Python :: 3.13
Requires-Dist: click (>=8.1.7,<9.0.0)
Requires-Dist: jsonschema (>=4.22.0,<5.0.0)
Requires-Dist: requests (>=2.32.2,<3.0.0)
Requires-Dist: sqlalchemy (>=2.0.30,<3.0.0)
Requires-Dist: sqlalchemy-utils (>=0.41.2,<0.42.0)
